DomFu/__init__.py
DomFu/__main__.py
DomFu_test-1.0.0.dist-info/LICENSE.txt
DomFu_test-1.0.0.dist-info/METADATA
DomFu_test-1.0.0.dist-info/WHEEL
DomFu_test-1.0.0.dist-info/entry_points.txt
DomFu_test-1.0.0.dist-info/top_level.txt
DomFu_test-1.0.0.dist-info/RECORD
