Metadata-Version: 2.1
Name: DomFu-test
Version: 1.0.0
Summary: A CLI app to find domains and subdomains of a given domain
Home-page: http://pypi.python.org/pypi/domfu/
Author: Suman Basuli
Author-email: thinisadhu@gmail.com
License: LICENSE.txt
Platform: UNKNOWN
Requires-Dist: fire
Requires-Dist: requests
Requires-Dist: validators
Requires-Dist: yaspin
